bintest/__init__.py
bintest/bintest.py
bintest-0.3.0.dist-info/WHEEL
bintest-0.3.0.dist-info/METADATA
bintest-0.3.0.dist-info/RECORD
